{
    "/js/app.js": "/js/app.js?id=4e45b2e572bbeadce9a3",
    "/css/app.css": "/css/app.css?id=38f644fb23898443dcaa",
    "/css/frontendapp.css": "/css/frontendapp.css?id=970ff98898a3bc983cff",
    "/css/style.css": "/css/style.css?id=6832e4a006bc86a25d5c",
    "/css/custom.css": "/css/custom.css?id=274a1ed1a83f0b9774aa",
    "/css/backendapp.css": "/css/backendapp.css?id=e6f5b0219236883c7eaa",
    "/css/backendcustom.css": "/css/backendcustom.css?id=ad513f1e41b010b80bac",
    "/css/sb-admin-2.css": "/css/sb-admin-2.css?id=94a7a6d39c297da22915"
}
